<BackupInst xmlns="http://www.microsoft.com/GroupPolicy/GPOOperations/Manifest"><GPOGuid><![CDATA[{ECA4D0C9-D6CF-41C5-9106-C1ECC6E15B8E}]]></GPOGuid><GPODomain><![CDATA[windomain.local]]></GPODomain><GPODomainGuid><![CDATA[{775b304a-1fff-4879-952d-f43d7fdbd0db}]]></GPODomainGuid><GPODomainController><![CDATA[dc.windomain.local]]></GPODomainController><BackupTime><![CDATA[2020-04-22T10:11:08]]></BackupTime><ID><![CDATA[{B3599B7F-DDD4-44C3-957C-604E5A5C484C}]]></ID><Comment><![CDATA[]]></Comment><GPODisplayName><![CDATA[Enable Claims Support]]></GPODisplayName></BackupInst>
